{
  "ComponentIndexes": {},
  "ControlUniqueGuids": {},
  "ControlUniqueIds": {
    "Add_Desc": 29,
    "Add_Image": 19,
    "Add_Title": 14,
    "AddForm": 13,
    "AddNew": 4,
    "AddPictureImage_Add": 24,
    "AddPictureImage_Edit": 107,
    "App": 1,
    "BodyContAdd": 12,
    "BodyContDash": 43,
    "BodyContView": 90,
    "BreadCrumbGallery": 83,
    "Button_AddNew": 66,
    "Button_Cancel_Add": 10,
    "Button_Cancel_Edit": 114,
    "Button_DeleteImage_Add": 20,
    "Button_DeleteImage_Edit": 108,
    "Button_DeleteTicket": 76,
    "Button_Save_Add": 11,
    "Button_Save_Edit": 115,
    "Circle1": 85,
    "CreatedCont": 73,
    "CreatedInfo": 75,
    "DashAuthor": 54,
    "Dashboard": 34,
    "DashCat": 49,
    "DashClick": 48,
    "DashDesc": 61,
    "DashDnT": 58,
    "DashEmail": 56,
    "DashGallery": 44,
    "DashHeaderA": 8,
    "DashHeaderD": 38,
    "DashHeaderV": 71,
    "DashLogoA": 7,
    "DashLogoD": 37,
    "DashLogoV": 70,
    "DashTickets": 46,
    "DataCardKeyDesc_Add": 31,
    "DataCardKeyDesc_Edit": 100,
    "DataCardKeyImage_Add": 22,
    "DataCardKeyImage_Edit": 105,
    "DataCardKeyTitle_Add": 16,
    "DataCardKeyTitle_Edit": 94,
    "DataCardValueDesc_Add": 32,
    "DataCardValueDesc_Edit": 101,
    "DataCardValueTitle_Add": 17,
    "DataCardValueTitle_Edit": 96,
    "Date": 59,
    "Edit_Desc": 98,
    "Edit_Image": 103,
    "Edit_Title": 92,
    "EditForm": 91,
    "EmailCont": 80,
    "EmailInfo": 82,
    "ErrorMessageDesc_Add": 33,
    "ErrorMessageDesc_Edit": 102,
    "ErrorMessageImage_Add": 28,
    "ErrorMessageImage_Edit": 112,
    "ErrorMessageTitle_Add": 18,
    "ErrorMessageTitle_Edit": 97,
    "FooterContAdd": 9,
    "FooterContDash": 65,
    "FooterContView": 113,
    "format_Add": 27,
    "format_Edit": 111,
    "galleryTemplate1": 84,
    "galleryTemplate4_1": 47,
    "HeaderContAdd": 6,
    "HeaderContDash": 36,
    "HeaderContView": 69,
    "Host": 3,
    "Icon_upload_Add": 25,
    "Icon_upload_Edit": 109,
    "Icon1": 86,
    "ID_Dash": 55,
    "ImageImage_Add": 23,
    "ImageImage_Edit": 106,
    "ImagePreview": 51,
    "Label_Created": 74,
    "Label_DashAuthor": 53,
    "Label_DashEmail": 57,
    "Label_DashTickets": 45,
    "Label_Email": 81,
    "Label_User": 78,
    "Label4": 89,
    "NoImage": 62,
    "NoImage_Label1": 63,
    "NoImage_Label2": 64,
    "ParentContAdd": 5,
    "ParentContDash": 35,
    "ParentContView": 68,
    "PHimage": 52,
    "Rectangle1": 88,
    "Rectangle2": 87,
    "RefreshIcon": 42,
    "SearchBarCont": 39,
    "SearchIcon": 41,
    "SearchTicket": 40,
    "StarVisibleDesc_Add": 30,
    "StarVisibleDesc_Edit": 99,
    "StarVisibleImage_Add": 21,
    "StarVisibleImage_Edit": 104,
    "StarVisibleTitle_Add": 15,
    "StarVisibleTitle_Edit": 93,
    "StatusButton": 50,
    "TextInputTitle_Edit": 95,
    "Time": 60,
    "upload_Add": 26,
    "upload_Edit": 110,
    "UserCont": 77,
    "UserInfo": 79,
    "UserInfoCont": 72,
    "ViewEdit": 67
  },
  "FunctionParamsInvariantScripts": {},
  "FunctionParamsInvariantScriptsOnInstances": {},
  "HeaderLastSavedDateTimeUTC": "05/14/2024 16:01:15",
  "IsLegacyComponentAllowGlobalScopeCase": false,
  "LocalConnectionIDReferences": {
    "0187e4a0-d356-4e03-9fb3-2b07cd44e52d": "\"/providers/microsoft.powerapps/apis/shared_office365users/connections/4d45ee3dbdb04537ae0eb70f5c0df424\"",
    "31542835-9102-43de-9b1d-5a1ce7fde00a": "\"/providers/microsoft.powerapps/apis/shared_sharepointonline/connections/62fe50c64e55460f91dc6db5037e5d9d\""
  },
  "LocalDatabaseReferencesAsEmpty": true,
  "LocalResourceFileNames": {
    "download": "0001.png",
    "download_1": "0002.png",
    "file-upload_10015516": "0003.png",
    "PH -2": "0004.png",
    "Picture1": "0005.png",
    "technufllc_logo": "0006.jpeg",
    "upload_10233773": "0008.png",
    "uploading_4355783": "0007.png",
    "vectorstock_42783342": "0009.png"
  },
  "LocalResourceRootPaths": {
    "download": "https://docserverpwaprodeus.blob.core.windows.net/c4db674c-591c-4041-9207-ae6c4192cddd-1/resource/Assets0Images00001.png?skoid=58690ece-ec83-4ce2-9ce8-883d4d6a54ee&sktid=975f013f-7f24-47e8-a7d3-abc4752bf346&skt=2024-05-14T13%3A26%3A55Z&ske=2024-05-15T13%3A41%3A55Z&sks=b&skv=2022-11-02&sv=2022-11-02&spr=https&se=2024-05-15T13%3A41%3A55Z&sr=b&sp=r&sig=wDDn7gQDme421ix%2F78QDR2y%2FnTwaBBxreUP2UNVEpHQ%3D",
    "download_1": "https://docserverpwaprodeus.blob.core.windows.net/c4db674c-591c-4041-9207-ae6c4192cddd-1/resource/Assets0Images00002.png?skoid=58690ece-ec83-4ce2-9ce8-883d4d6a54ee&sktid=975f013f-7f24-47e8-a7d3-abc4752bf346&skt=2024-05-14T13%3A26%3A55Z&ske=2024-05-15T13%3A41%3A55Z&sks=b&skv=2022-11-02&sv=2022-11-02&spr=https&se=2024-05-15T13%3A41%3A55Z&sr=b&sp=r&sig=CouLlvyoPRHdRR91gLCs03romxo82KVRUjQMQFDWad4%3D",
    "file-upload_10015516": "https://docserverpwaprodeus.blob.core.windows.net/c4db674c-591c-4041-9207-ae6c4192cddd-1/resource/Assets0Images00003.png?skoid=58690ece-ec83-4ce2-9ce8-883d4d6a54ee&sktid=975f013f-7f24-47e8-a7d3-abc4752bf346&skt=2024-05-14T13%3A26%3A55Z&ske=2024-05-15T13%3A41%3A55Z&sks=b&skv=2022-11-02&sv=2022-11-02&spr=https&se=2024-05-15T13%3A41%3A55Z&sr=b&sp=r&sig=Hns4WohYmbt2WjE%2BwXoLG%2FrSKb2Vm5u3QjL1ZCsU%2FhU%3D",
    "PH -2": "https://docserverpwaprodeus.blob.core.windows.net/c4db674c-591c-4041-9207-ae6c4192cddd-1/resource/Assets0Images00004.png?skoid=58690ece-ec83-4ce2-9ce8-883d4d6a54ee&sktid=975f013f-7f24-47e8-a7d3-abc4752bf346&skt=2024-05-14T13%3A26%3A55Z&ske=2024-05-15T13%3A41%3A55Z&sks=b&skv=2022-11-02&sv=2022-11-02&spr=https&se=2024-05-15T13%3A41%3A55Z&sr=b&sp=r&sig=tQWKWuPgCLVDI6f0nN2Yw%2BGp5zdderbAq2oNmvxIaCM%3D",
    "Picture1": "https://docserverpwaprodeus.blob.core.windows.net/c4db674c-591c-4041-9207-ae6c4192cddd-1/resource/Assets0Images00005.png?skoid=58690ece-ec83-4ce2-9ce8-883d4d6a54ee&sktid=975f013f-7f24-47e8-a7d3-abc4752bf346&skt=2024-05-14T13%3A26%3A55Z&ske=2024-05-15T13%3A41%3A55Z&sks=b&skv=2022-11-02&sv=2022-11-02&spr=https&se=2024-05-15T13%3A41%3A55Z&sr=b&sp=r&sig=hAupnDqMgsrTMMgq4mtSIWfVpkpbjZi4qaBxKBc6FEI%3D",
    "technufllc_logo": "https://docserverpwaprodeus.blob.core.windows.net/c4db674c-591c-4041-9207-ae6c4192cddd-1/resource/Assets0Images00006.jpeg?skoid=58690ece-ec83-4ce2-9ce8-883d4d6a54ee&sktid=975f013f-7f24-47e8-a7d3-abc4752bf346&skt=2024-05-14T13%3A26%3A55Z&ske=2024-05-15T13%3A41%3A55Z&sks=b&skv=2022-11-02&sv=2022-11-02&spr=https&se=2024-05-15T13%3A41%3A55Z&sr=b&sp=r&sig=i%2Fa%2BSJYaJTt9N8Y3GaqkDvFJwvD6rAi2hClSKWqUYu0%3D",
    "upload_10233773": "https://docserverpwaprodeus.blob.core.windows.net/c4db674c-591c-4041-9207-ae6c4192cddd-1/resource/Assets0Images00008.png?skoid=58690ece-ec83-4ce2-9ce8-883d4d6a54ee&sktid=975f013f-7f24-47e8-a7d3-abc4752bf346&skt=2024-05-14T13%3A26%3A55Z&ske=2024-05-15T13%3A41%3A55Z&sks=b&skv=2022-11-02&sv=2022-11-02&spr=https&se=2024-05-15T13%3A41%3A55Z&sr=b&sp=r&sig=%2B7V1ukwhgWdf8wO1AL6My%2FZYGgtBRYpRl5YaPridPYk%3D",
    "uploading_4355783": "https://docserverpwaprodeus.blob.core.windows.net/c4db674c-591c-4041-9207-ae6c4192cddd-1/resource/Assets0Images00007.png?skoid=58690ece-ec83-4ce2-9ce8-883d4d6a54ee&sktid=975f013f-7f24-47e8-a7d3-abc4752bf346&skt=2024-05-14T13%3A26%3A55Z&ske=2024-05-15T13%3A41%3A55Z&sks=b&skv=2022-11-02&sv=2022-11-02&spr=https&se=2024-05-15T13%3A41%3A55Z&sr=b&sp=r&sig=38eqkjI4diF3TU0F5bI5GZbMUjihHUZPNnhzwTqgRAE%3D",
    "vectorstock_42783342": "https://docserverpwaprodeus.blob.core.windows.net/c4db674c-591c-4041-9207-ae6c4192cddd-1/resource/Assets0Images00009.png?skoid=58690ece-ec83-4ce2-9ce8-883d4d6a54ee&sktid=975f013f-7f24-47e8-a7d3-abc4752bf346&skt=2024-05-14T13%3A26%3A55Z&ske=2024-05-15T13%3A41%3A55Z&sks=b&skv=2022-11-02&sv=2022-11-02&spr=https&se=2024-05-15T13%3A41%3A55Z&sr=b&sp=r&sig=7DxIfwGIedPmFeLzVnxA5H0Khs0Mj7S6IvkConiy7NQ%3D"
  },
  "OrderComponentMetadata": {},
  "OrderComponentTemplate": {},
  "OrderDataSource": {
    "ComboBoxSample": 1,
    "ConcatenatedList": 7,
    "CustomGallerySample": 2,
    "Documents": 3,
    "DropDownSample": 4,
    "Office365Users": 0,
    "Technuf Service Request": 5,
    "Work Progress Tracker": 6
  },
  "OrderGroupControls": {},
  "OrderPcfTemplate": {},
  "OrderTemplate": {},
  "OrderXMLTemplate": {
    "addMedia": 7,
    "button": 3,
    "circle": 10,
    "dropdown": 5,
    "form": 4,
    "gallery": 9,
    "groupContainer": 0,
    "icon": 6,
    "image": 1,
    "label": 2,
    "rectangle": 11,
    "text": 8
  },
  "OverridablePropertiesEntry": {
    "Add_Desc": {},
    "Add_Image": {},
    "Add_Title": {},
    "AddForm": {},
    "AddNew": {},
    "AddPictureImage_Add": {},
    "AddPictureImage_Edit": {},
    "App": {},
    "BodyContAdd": {},
    "BodyContDash": {},
    "BodyContView": {},
    "BreadCrumbGallery": {},
    "Button_AddNew": {},
    "Button_Cancel_Add": {},
    "Button_Cancel_Edit": {},
    "Button_DeleteImage_Add": {},
    "Button_DeleteImage_Edit": {},
    "Button_DeleteTicket": {},
    "Button_Save_Add": {},
    "Button_Save_Edit": {},
    "Circle1": {},
    "CreatedCont": {},
    "CreatedInfo": {},
    "DashAuthor": {},
    "Dashboard": {},
    "DashCat": {},
    "DashClick": {},
    "DashDesc": {},
    "DashDnT": {},
    "DashEmail": {},
    "DashGallery": {},
    "DashHeaderA": {},
    "DashHeaderD": {},
    "DashHeaderV": {},
    "DashLogoA": {},
    "DashLogoD": {},
    "DashLogoV": {},
    "DashTickets": {},
    "DataCardKeyDesc_Add": {},
    "DataCardKeyDesc_Edit": {},
    "DataCardKeyImage_Add": {},
    "DataCardKeyImage_Edit": {},
    "DataCardKeyTitle_Add": {},
    "DataCardKeyTitle_Edit": {},
    "DataCardValueDesc_Add": {},
    "DataCardValueDesc_Edit": {},
    "DataCardValueTitle_Add": {},
    "DataCardValueTitle_Edit": {},
    "Date": {},
    "Edit_Desc": {},
    "Edit_Image": {},
    "Edit_Title": {},
    "EditForm": {},
    "EmailCont": {},
    "EmailInfo": {},
    "ErrorMessageDesc_Add": {},
    "ErrorMessageDesc_Edit": {},
    "ErrorMessageImage_Add": {},
    "ErrorMessageImage_Edit": {},
    "ErrorMessageTitle_Add": {},
    "ErrorMessageTitle_Edit": {},
    "FooterContAdd": {},
    "FooterContDash": {},
    "FooterContView": {},
    "format_Add": {},
    "format_Edit": {},
    "galleryTemplate1": {},
    "galleryTemplate4_1": {},
    "HeaderContAdd": {},
    "HeaderContDash": {},
    "HeaderContView": {},
    "Host": {},
    "Icon_upload_Add": {},
    "Icon_upload_Edit": {},
    "Icon1": {},
    "ID_Dash": {},
    "ImageImage_Add": {},
    "ImageImage_Edit": {},
    "ImagePreview": {},
    "Label_Created": {},
    "Label_DashAuthor": {},
    "Label_DashEmail": {},
    "Label_DashTickets": {},
    "Label_Email": {},
    "Label_User": {},
    "Label4": {},
    "NoImage": {},
    "NoImage_Label1": {},
    "NoImage_Label2": {},
    "ParentContAdd": {},
    "ParentContDash": {},
    "ParentContView": {},
    "PHimage": {},
    "Rectangle1": {},
    "Rectangle2": {},
    "RefreshIcon": {},
    "SearchBarCont": {},
    "SearchIcon": {},
    "SearchTicket": {},
    "StarVisibleDesc_Add": {},
    "StarVisibleDesc_Edit": {},
    "StarVisibleImage_Add": {},
    "StarVisibleImage_Edit": {},
    "StarVisibleTitle_Add": {},
    "StarVisibleTitle_Edit": {},
    "StatusButton": {},
    "TextInputTitle_Edit": {},
    "Time": {},
    "upload_Add": {},
    "upload_Edit": {},
    "UserCont": {},
    "UserInfo": {},
    "UserInfoCont": {},
    "ViewEdit": {}
  },
  "PCFDynamicSchemaForIRRetrievalEntry": {},
  "PCFTemplateEntry": {},
  "PublishOrderIndices": {
    "Add_Desc": 104,
    "Add_Image": 94,
    "Add_Title": 89,
    "AddForm": 88,
    "AddNew": 1,
    "AddPictureImage_Add": 99,
    "AddPictureImage_Edit": 71,
    "App": 0,
    "BodyContAdd": 87,
    "BodyContDash": 8,
    "BodyContView": 54,
    "BreadCrumbGallery": 47,
    "Button_AddNew": 31,
    "Button_Cancel_Add": 85,
    "Button_Cancel_Edit": 78,
    "Button_DeleteImage_Add": 95,
    "Button_DeleteImage_Edit": 72,
    "Button_DeleteTicket": 40,
    "Button_Save_Add": 86,
    "Button_Save_Edit": 79,
    "Circle1": 49,
    "CreatedCont": 37,
    "CreatedInfo": 39,
    "DashAuthor": 19,
    "Dashboard": 38,
    "DashCat": 14,
    "DashClick": 13,
    "DashDesc": 26,
    "DashDnT": 23,
    "DashEmail": 21,
    "DashGallery": 9,
    "DashHeaderA": 83,
    "DashHeaderD": 3,
    "DashHeaderV": 35,
    "DashLogoA": 82,
    "DashLogoD": 2,
    "DashLogoV": 34,
    "DashTickets": 11,
    "DataCardKeyDesc_Add": 106,
    "DataCardKeyDesc_Edit": 64,
    "DataCardKeyImage_Add": 97,
    "DataCardKeyImage_Edit": 69,
    "DataCardKeyTitle_Add": 91,
    "DataCardKeyTitle_Edit": 58,
    "DataCardValueDesc_Add": 107,
    "DataCardValueDesc_Edit": 65,
    "DataCardValueTitle_Add": 92,
    "DataCardValueTitle_Edit": 60,
    "Date": 24,
    "Edit_Desc": 62,
    "Edit_Image": 67,
    "Edit_Title": 56,
    "EditForm": 55,
    "EmailCont": 44,
    "EmailInfo": 46,
    "ErrorMessageDesc_Add": 108,
    "ErrorMessageDesc_Edit": 66,
    "ErrorMessageImage_Add": 103,
    "ErrorMessageImage_Edit": 76,
    "ErrorMessageTitle_Add": 93,
    "ErrorMessageTitle_Edit": 61,
    "FooterContAdd": 84,
    "FooterContDash": 30,
    "FooterContView": 77,
    "format_Add": 102,
    "format_Edit": 75,
    "galleryTemplate1": 48,
    "galleryTemplate4_1": 12,
    "HeaderContAdd": 81,
    "HeaderContDash": 1,
    "HeaderContView": 33,
    "Host": 0,
    "Icon_upload_Add": 100,
    "Icon_upload_Edit": 73,
    "Icon1": 50,
    "ID_Dash": 20,
    "ImageImage_Add": 98,
    "ImageImage_Edit": 70,
    "ImagePreview": 16,
    "Label_Created": 38,
    "Label_DashAuthor": 18,
    "Label_DashEmail": 22,
    "Label_DashTickets": 10,
    "Label_Email": 45,
    "Label_User": 42,
    "Label4": 53,
    "NoImage": 27,
    "NoImage_Label1": 28,
    "NoImage_Label2": 29,
    "ParentContAdd": 80,
    "ParentContDash": 0,
    "ParentContView": 32,
    "PHimage": 17,
    "Rectangle1": 52,
    "Rectangle2": 51,
    "RefreshIcon": 7,
    "SearchBarCont": 4,
    "SearchIcon": 6,
    "SearchTicket": 5,
    "StarVisibleDesc_Add": 105,
    "StarVisibleDesc_Edit": 63,
    "StarVisibleImage_Add": 96,
    "StarVisibleImage_Edit": 68,
    "StarVisibleTitle_Add": 90,
    "StarVisibleTitle_Edit": 57,
    "StatusButton": 15,
    "TextInputTitle_Edit": 59,
    "Time": 25,
    "upload_Add": 101,
    "upload_Edit": 74,
    "UserCont": 41,
    "UserInfo": 43,
    "UserInfoCont": 36,
    "ViewEdit": 75
  },
  "ResourcesJsonIndices": {
    "Image-download": 1,
    "Image-download_1": 2,
    "Image-file-upload_10015516": 3,
    "Image-PH -2": 4,
    "Image-Picture1": 5,
    "Image-SampleImage": 0,
    "Image-technufllc_logo": 6,
    "Image-upload_10233773": 8,
    "Image-uploading_4355783": 7,
    "Image-vectorstock_42783342": 9
  },
  "RuleScreenIdWithoutScreen": {},
  "TemplateVersions": {},
  "VolatileProperties": {
    "AnalysisLoadTime": 0.7351205,
    "ControlCount": {
      "addMedia": 2,
      "button": 7,
      "circle": 1,
      "dropdown": 2,
      "form": 2,
      "gallery": 2,
      "galleryTemplate": 2,
      "groupContainer": 18,
      "icon": 8,
      "image": 10,
      "label": 43,
      "rectangle": 2,
      "screen": 3,
      "text": 4,
      "typedDataCard": 6
    },
    "DeserializationLoadTime": 2.1886919
  },
  "WasLocalDatabaseReferencesEmpty": true
}